dropbox_offline_backup-0.0.13.dist-info/DESCRIPTION.rst
dropbox_offline_backup-0.0.13.dist-info/METADATA
dropbox_offline_backup-0.0.13.dist-info/RECORD
dropbox_offline_backup-0.0.13.dist-info/WHEEL
dropbox_offline_backup-0.0.13.dist-info/entry_points.txt
dropbox_offline_backup-0.0.13.dist-info/metadata.json
dropbox_offline_backup-0.0.13.dist-info/top_level.txt
dropboxbackup/__init__.py
dropboxbackup/backup.py
dropboxbackup/config.py
