Metadata-Version: 2.0
Name: dropbox-offline-backup
Version: 0.0.13
Summary: Backup your Dropbox offline
Home-page: https://github.com/764664/dropbox-offline-backup
Author: Jie Lu
Author-email: 764664@gmail.com
License: MIT
Platform: UNKNOWN
Requires-Dist: dropbox
